geniusrise_audio/__init__.py
geniusrise_audio/base/__init__.py
geniusrise_audio/base/api.py
geniusrise_audio/base/bulk.py
geniusrise_audio/base/communication.py
geniusrise_audio/base/fine_tune.py
geniusrise_audio/s2t/__init__.py
geniusrise_audio/s2t/api.py
geniusrise_audio/s2t/bulk.py
geniusrise_audio/s2t/fine_tune.py
geniusrise_audio/s2t/util.py
geniusrise_audio/t2s/__init__.py
geniusrise_audio/t2s/api.py
geniusrise_audio/t2s/bulk.py
geniusrise_audio/t2s/fine_tune.py
geniusrise_audio/t2s/util.py
geniusrise_audio-0.1.12.dist-info/LICENSE
geniusrise_audio-0.1.12.dist-info/METADATA
geniusrise_audio-0.1.12.dist-info/WHEEL
geniusrise_audio-0.1.12.dist-info/top_level.txt
geniusrise_audio-0.1.12.dist-info/RECORD
