Metadata-Version: 2.1
Name: geniusrise-audio
Version: 0.1.12
Summary: audio bolts for geniusrise
Home-page: https://github.com/geniusrise/geniusrise-audio
Author: ixaxaar
Author-email: ixaxaar@geniusrise.ai
Project-URL: Bug Reports, https://github.com/geniusrise/geniusrise-audio/issues
Project-URL: Source, https://github.com/geniusrise/geniusrise-audio
Project-URL: Documentation, https://docs.geniusrise.ai/
Keywords: mlops,llm,geniusrise,machine learning,data processing
Classifier: Development Status :: 3 - Alpha
Classifier: Intended Audience :: Developers
Classifier: Topic :: Software Development :: Build Tools
Classifier: License :: OSI Approved :: Apache Software License
Classifier: Programming Language :: Python :: 3.10
Classifier: Programming Language :: Python :: 3.11
Classifier: Programming Language :: Python :: 3.12
Classifier: Operating System :: OS Independent
Requires-Python: >=3.10
License-File: LICENSE
Requires-Dist: geniusrise ==0.1.7
Requires-Dist: torch ==2.1.2
Requires-Dist: accelerate ==0.27.2
Requires-Dist: transformers ==4.38.1
Requires-Dist: evaluate ==0.4.1
Requires-Dist: datasets ==2.16.1
Requires-Dist: autoawq ==0.2.2
Requires-Dist: auto-gptq ==0.7.0
Requires-Dist: bitsandbytes ==0.42.0
Requires-Dist: CherryPy ==18.9.0
Requires-Dist: flash-attn ==2.4.2
Requires-Dist: peft ==0.7.1
Requires-Dist: gunicorn ==21.2.0
Requires-Dist: trl ==0.7.10
Requires-Dist: sentence-transformers ==2.2.2
Requires-Dist: nbformat ==5.9.2
Requires-Dist: pydub ==0.25.1
Requires-Dist: torchaudio <=2.2.0
Requires-Dist: soundfile ==0.12.1
Requires-Dist: librosa ==0.10.1
Requires-Dist: pyctcdecode ==0.5.0
Requires-Dist: huggingface-hub ==0.20.3
Requires-Dist: kenlm ==0.2.0
Requires-Dist: safetensors ==0.4.1
Requires-Dist: einops ==0.7.0
Requires-Dist: packaging ==23.2
Requires-Dist: optimum ==1.16.2
Requires-Dist: textwrap3 ==0.9.2
Requires-Dist: nltk ==3.8.1
Requires-Dist: pyarrow >=9.0.0
Requires-Dist: absl-py ==2.1.0
Requires-Dist: pandas ==1.3.5
Requires-Dist: multiprocess ==0.70.15
Requires-Dist: whispercpp ==0.0.17
Provides-Extra: dev
Requires-Dist: check-manifest ; extra == 'dev'
Provides-Extra: test
Requires-Dist: coverage ; extra == 'test'
